baseqCNV/__init__.py
baseqCNV/align.py
baseqCNV/bincount.py
baseqCNV/cmd.py
baseqCNV/command.py
baseqCNV/config.py
baseqCNV/fastq_files.py
baseqCNV/normalize.py
baseqCNV/pipeline.py
baseqCNV/process.py
baseqCNV/results.py
baseqCNV/segment.py
baseqCNV/plots/__init__.py
baseqCNV/plots/genome.py
baseqCNV/plots/genome_overlap.py
baseqCNV/plots/region.py
baseqCNV-1.1.dist-info/DESCRIPTION.rst
baseqCNV-1.1.dist-info/METADATA
baseqCNV-1.1.dist-info/RECORD
baseqCNV-1.1.dist-info/WHEEL
baseqCNV-1.1.dist-info/entry_points.txt
baseqCNV-1.1.dist-info/metadata.json
baseqCNV-1.1.dist-info/top_level.txt
